{
    "results": [
        {
            "simulator_statevector": {
                "00": 2009,
                "11": 1991
            }
        },
        {
            "simulator_mps": {
                "11": 999,
                "00": 1001
            }
        },
        {
            "ibmq_qasm_simulator": {
                "11": 998,
                "00": 1002
            }
        },
        {
            "simulator_extended_stabilizer": {
                "00": 1020,
                "11": 980
            }
        }
    ],
    "distribution": {
        "00": "50.34%",
        "11": "49.66%"
    }
}